LICENSE.txt
MANIFEST.in
README
adsense_scraper.py
setup.py
adsense_scraper.egg-info/PKG-INFO
adsense_scraper.egg-info/SOURCES.txt
adsense_scraper.egg-info/dependency_links.txt
adsense_scraper.egg-info/requires.txt
adsense_scraper.egg-info/top_level.txt