Metadata-Version: 1.0
Name: adsense-scraper
Version: 0.5
Summary: Scrapes Google AdSense earnings data with Python using Twill
Home-page: http://github.com/etrepum/adsense_scraper/tree/master
Author: Bob Ippolito
Author-email: bob@redivi.com
License: MIT License
Platform: any
Classifier: Intended Audience :: Developers
Classifier: License :: OSI Approved :: MIT License
Classifier: Programming Language :: Python
Classifier: Topic :: Software Development :: Libraries :: Python Modules
